MANIFEST.in
README.rst
setup.py
roan/__init__.py
roan/models.py
roan.egg-info/PKG-INFO
roan.egg-info/SOURCES.txt
roan.egg-info/dependency_links.txt
roan.egg-info/requires.txt
roan.egg-info/top_level.txt