Metadata-Version: 1.0
Name: roan
Version: 0.1
Summary: Django per-model cache purging
Home-page: UNKNOWN
Author: CobraTeam
Author-email: francisco@franciscosouza.net
License: UNKNOWN
Platform: UNKNOWN
